arcane/credentials/__init__.py
arcane/credentials/credentials.py
arcane/credentials/exceptions.py
arcane_credentials-0.1.1.dist-info/METADATA
arcane_credentials-0.1.1.dist-info/WHEEL
arcane_credentials-0.1.1.dist-info/RECORD
