Metadata-Version: 2.1
Name: arcane-credentials
Version: 0.1.1
Summary: Package description
Author: Arcane
Author-email: product@arcane.run
Requires-Python: >=3.6,<4.0
Classifier: Programming Language :: Python :: 3
Classifier: Programming Language :: Python :: 3.6
Classifier: Programming Language :: Python :: 3.7
Classifier: Programming Language :: Python :: 3.8
Classifier: Programming Language :: Python :: 3.9
Classifier: Programming Language :: Python :: 3.10
Classifier: Programming Language :: Python :: 3.11
Requires-Dist: arcane-core (>=1.7.0,<2.0.0)
Requires-Dist: arcane-datastore (>=1.1.0,<2.0.0)
Requires-Dist: arcane-secret (>=0.2.0,<0.3.0)
